numalogic/__init__.py
numalogic/_constants.py
numalogic/models/__init__.py
numalogic/models/autoencoder/__init__.py
numalogic/models/autoencoder/base.py
numalogic/models/autoencoder/factory.py
numalogic/models/autoencoder/pipeline.py
numalogic/models/autoencoder/variants/__init__.py
numalogic/models/autoencoder/variants/conv.py
numalogic/models/autoencoder/variants/lstm.py
numalogic/models/autoencoder/variants/transformer.py
numalogic/models/autoencoder/variants/vanilla.py
numalogic/models/forecast/__init__.py
numalogic/models/forecast/variants/__init__.py
numalogic/models/forecast/variants/naive.py
numalogic/models/threshold/__init__.py
numalogic/models/threshold/_std.py
numalogic/postprocess.py
numalogic/preprocess/__init__.py
numalogic/preprocess/datasets.py
numalogic/preprocess/transformer.py
numalogic/registry/__init__.py
numalogic/registry/artifact.py
numalogic/registry/mlflow_registry.py
numalogic/synthetic/__init__.py
numalogic/synthetic/anomalies.py
numalogic/synthetic/sparsity.py
numalogic/synthetic/timeseries.py
numalogic/tests/__init__.py
numalogic/tests/models/__init__.py
numalogic/tests/models/autoencoder/__init__.py
numalogic/tests/models/autoencoder/test_factory.py
numalogic/tests/models/autoencoder/test_pipeline.py
numalogic/tests/models/autoencoder/variants/__init__.py
numalogic/tests/models/autoencoder/variants/test_conv.py
numalogic/tests/models/autoencoder/variants/test_lstm.py
numalogic/tests/models/autoencoder/variants/test_transformers.py
numalogic/tests/models/autoencoder/variants/test_vanilla.py
numalogic/tests/models/forecast/__init__.py
numalogic/tests/models/forecast/test_naive.py
numalogic/tests/preprocess/__init__.py
numalogic/tests/preprocess/test_datasets.py
numalogic/tests/preprocess/test_transformer.py
numalogic/tests/registry/__init__.py
numalogic/tests/registry/_mlflow_utils.py
numalogic/tests/registry/test_mlflow_registry.py
numalogic/tests/resources/data/interactionstatus.csv
numalogic/tests/synthetic/__init__.py
deletekb-0.0.4.dist-info/LICENSE
deletekb-0.0.4.dist-info/WHEEL
deletekb-0.0.4.dist-info/METADATA
deletekb-0.0.4.dist-info/RECORD
